connotati/__init__.py
connotati-0.1.0.2.dist-info/LICENSE
connotati-0.1.0.2.dist-info/METADATA
connotati-0.1.0.2.dist-info/WHEEL
connotati-0.1.0.2.dist-info/entry_points.txt
connotati-0.1.0.2.dist-info/top_level.txt
connotati-0.1.0.2.dist-info/RECORD
