Metadata-Version: 2.1
Name: connotati
Version: 0.1.0.2
Summary: Start gtk apps with given theme
Home-page: https://github.com/tallero/connotati
Author: Pellegrino Prevete
Author-email: pellegrinoprevete@gmail.com
License: UNKNOWN
Platform: UNKNOWN
Classifier: Programming Language :: Python :: 3
Classifier: License :: OSI Approved :: GNU General Public License v3 or later (GPLv3+)
Classifier: Operating System :: Unix
